bogus_honeypot/__init__.py
python_bogus_project_honeypot-1531939498.3.dist-info/DESCRIPTION.rst
python_bogus_project_honeypot-1531939498.3.dist-info/METADATA
python_bogus_project_honeypot-1531939498.3.dist-info/RECORD
python_bogus_project_honeypot-1531939498.3.dist-info/WHEEL
python_bogus_project_honeypot-1531939498.3.dist-info/metadata.json
python_bogus_project_honeypot-1531939498.3.dist-info/pbr.json
python_bogus_project_honeypot-1531939498.3.dist-info/top_level.txt
